connexion_plus/Application.py
connexion_plus/MultipleResourceResolver.py
connexion_plus/Optimizer.py
connexion_plus/TracingHandler.py
connexion_plus/Util.py
connexion_plus/__init__.py
connexion_plus-0.49.dist-info/LICENSE.txt
connexion_plus-0.49.dist-info/METADATA
connexion_plus-0.49.dist-info/WHEEL
connexion_plus-0.49.dist-info/top_level.txt
connexion_plus-0.49.dist-info/RECORD
