Metadata-Version: 2.1
Name: connexion-plus
Version: 0.49
Summary: Connexion with benefits for microservices
Home-page: https://github.com/Heiss/connexion-plus
Author: Peter Heiss
Author-email: peter.heiss@uni-muenster.de
License: MIT
Keywords: connexion,microservice,tracing,prometheus,jaeger
Classifier: Development Status :: 3 - Alpha
Classifier: Intended Audience :: Developers
Classifier: Topic :: Software Development :: Build Tools
Classifier: License :: OSI Approved :: MIT License
Classifier: Programming Language :: Python :: 3
Classifier: Programming Language :: Python :: 3.6
Classifier: Programming Language :: Python :: 3.7
Classifier: Programming Language :: Python :: 3.8
Requires-Python: >=3.6
License-File: LICENSE.txt
Requires-Dist: connexion
Requires-Dist: jaeger-client
Requires-Dist: prometheus-flask-exporter
Requires-Dist: requests
Requires-Dist: opentracing-instrumentation
Requires-Dist: Flask-Opentracing
Requires-Dist: htmlmin
Requires-Dist: flask-cors
Requires-Dist: Flask-APScheduler
Requires-Dist: redis-pubsub-dict-wo-cluster
Requires-Dist: redis
